kabardian_translator/__init__.py
kabardian_translator/app.py
kabardian_translator/cli.py
kabardian_translator/download_models.py
kabardian_translator/translation_service.py
kabardian_translator/transliterator.py
kabardian_translator/tts_service.py
kabardian_translator/templates/index.html
kabardian_translator-2.0.0.data/data/share/kabardian-translator/LICENSE
kabardian_translator-2.0.0.data/data/share/kabardian-translator/README.md
kabardian_translator-2.0.0.dist-info/licenses/LICENSE
kabardian_translator-2.0.0.dist-info/METADATA
kabardian_translator-2.0.0.dist-info/WHEEL
kabardian_translator-2.0.0.dist-info/entry_points.txt
kabardian_translator-2.0.0.dist-info/top_level.txt
kabardian_translator-2.0.0.dist-info/RECORD
