Metadata-Version: 2.4
Name: kabardian-translator
Version: 2.0.0
Summary: Multilingual translator for Kabardian and Caucasian languages with neural translation and speech synthesis
Home-page: https://github.com/kubataba/kabardian-translator
Author: Kubataba
Author-email: Kubataba <info@copperline.info>
Maintainer-email: Kubataba <info@copperline.info>
License-Expression: CC-BY-NC-4.0
Platform: macOS
Platform: Linux
Platform: Windows
Provides: kabardian_translator
Requires-Python: >=3.11
License-File: LICENSE
Requires-Dist: flask>=3.0.0
Requires-Dist: torch>=2.1.0
Requires-Dist: transformers>=4.37.0
Requires-Dist: sentencepiece>=0.1.99
Requires-Dist: accelerate>=0.24.1
Requires-Dist: huggingface-hub>=0.20.3
Requires-Dist: soundfile>=0.12.1
Requires-Dist: numpy>=1.24.3
Requires-Dist: scipy>=1.11.0
Requires-Dist: torchaudio>=2.1.0
Requires-Dist: omegaconf>=2.3.0
Requires-Dist: silero-stress>=1.0.0
Requires-Dist: regex>=2023.10.3
Provides-Extra: audio
Requires-Dist: librosa>=0.10.0; extra == "audio"
Provides-Extra: dev
Requires-Dist: pytest>=7.0.0; extra == "dev"
Requires-Dist: black>=23.0.0; extra == "dev"
Requires-Dist: flake8>=6.0.0; extra == "dev"
Requires-Dist: mypy>=1.0.0; extra == "dev"
Requires-Dist: build>=0.10.0; extra == "dev"
Requires-Dist: twine>=4.0.0; extra == "dev"
Requires-Dist: pytest-cov>=4.1.0; extra == "dev"
Provides-Extra: gui
Requires-Dist: gradio>=4.0.0; extra == "gui"
Requires-Dist: ipywidgets>=8.0.0; extra == "gui"
Provides-Extra: full
Requires-Dist: librosa>=0.10.0; extra == "full"
Requires-Dist: gradio>=4.0.0; extra == "full"
Dynamic: author
Dynamic: home-page
Dynamic: license-file
Dynamic: platform
Dynamic: provides
Dynamic: requires-python
